AUTHORS.rst
CONTRIBUTING.rst
HISTORY.rst
LICENSE
MANIFEST.in
README.rst
setup.cfg
setup.py
docs/Makefile
docs/authors.rst
docs/conf.py
docs/contributing.rst
docs/history.rst
docs/index.rst
docs/installation.rst
docs/make.bat
docs/readme.rst
docs/usage.rst
tests/__init__.py
tests/test_visnet.py
visnetwork/__init__.py
visnetwork/cli.py
visnetwork.egg-info/PKG-INFO
visnetwork.egg-info/SOURCES.txt
visnetwork.egg-info/dependency_links.txt
visnetwork.egg-info/entry_points.txt
visnetwork.egg-info/not-zip-safe
visnetwork.egg-info/requires.txt
visnetwork.egg-info/top_level.txt
visnetwork/drawing/__init__.py
visnetwork/drawing/animate.py
visnetwork/drawing/base.py
visnetwork/drawing/continuous.py
visnetwork/drawing/discrete.py
visnetwork/drawing/unique.py
visnetwork/network/__init__.py
visnetwork/network/initialize.py
visnetwork/network/processing.py
visnetwork/utils/__init__.py
visnetwork/utils/convert_excel.py
visnetwork/utils/normalize_parameter.py
visnetwork/utils/save_fig.py
visnetwork/utils/unit_conversion.py