Metadata-Version: 2.1
Name: visnetwork
Version: 0.1.1
Summary: A python package for easy generation and customization of water network graphs.
Home-page: https://github.com/tylertrimble/visnet
Author: Tyler Trimble
Author-email: TylerL.Trimble@gmail.com
License: MIT license
Keywords: visnetwork
Classifier: Development Status :: 2 - Pre-Alpha
Classifier: Intended Audience :: Developers
Classifier: License :: OSI Approved :: MIT License
Classifier: Natural Language :: English
Classifier: Programming Language :: Python :: 3
Classifier: Programming Language :: Python :: 3.6
Classifier: Programming Language :: Python :: 3.7
Classifier: Programming Language :: Python :: 3.8
Requires-Python: >=3.7
License-File: LICENSE
License-File: AUTHORS.rst
